privateurl/__init__.py
privateurl/admin.py
privateurl/apps.py
privateurl/models.py
privateurl/settings.py
privateurl/signals.py
privateurl/urls.py
privateurl/views.py
privateurl/locale/en/LC_MESSAGES/django.mo
privateurl/locale/en/LC_MESSAGES/django.po
privateurl/locale/ru/LC_MESSAGES/django.mo
privateurl/locale/ru/LC_MESSAGES/django.po
privateurl/locale/uk/LC_MESSAGES/django.mo
privateurl/locale/uk/LC_MESSAGES/django.po
privateurl/migrations/0001_initial.py
privateurl/migrations/__init__.py
django_privateurl-1.4.0.dist-info/LICENSE.txt
django_privateurl-1.4.0.dist-info/METADATA
django_privateurl-1.4.0.dist-info/WHEEL
django_privateurl-1.4.0.dist-info/top_level.txt
django_privateurl-1.4.0.dist-info/RECORD
