Metadata-Version: 2.1
Name: django-privateurl
Version: 1.4.0
Summary: Django Private URL
Home-page: https://github.com/liminspace/django-privateurl
Author: Igor Melnyk @liminspace
Author-email: liminspace@gmail.com
License: MIT
Keywords: django,url,private,private url,django-privateurl
Platform: UNKNOWN
Classifier: Development Status :: 5 - Production/Stable
Classifier: Environment :: Web Environment
Classifier: Programming Language :: Python
Classifier: Programming Language :: Python :: 2
Classifier: Programming Language :: Python :: 2.7
Classifier: Programming Language :: Python :: 3
Classifier: Programming Language :: Python :: 3.5
Classifier: Programming Language :: Python :: 3.6
Classifier: Programming Language :: Python :: 3.7
Classifier: Programming Language :: Python :: 3.8
Classifier: Intended Audience :: Developers
Classifier: Topic :: Software Development :: Libraries
Classifier: Topic :: Software Development :: Libraries :: Application Frameworks
Classifier: Topic :: Software Development :: Libraries :: Python Modules
Classifier: Framework :: Django
Classifier: License :: OSI Approved :: MIT License
Requires-Dist: django (<3.2,>=1.8)
